ghostcoder/__init__.py
ghostcoder/actions/__init__.py
ghostcoder/actions/base.py
ghostcoder/actions/verify/__init__.py
ghostcoder/actions/verify/code_verifier.py
ghostcoder/actions/write_code/__init__.py
ghostcoder/actions/write_code/base.py
ghostcoder/actions/write_code/prompt.py
ghostcoder/api.py
ghostcoder/assistant.py
ghostcoder/benchmark/__init__.py
ghostcoder/benchmark/benchmark.py
ghostcoder/benchmark/prompts.py
ghostcoder/benchmark/utils.py
ghostcoder/callback.py
ghostcoder/codeblocks/__init__.py
ghostcoder/codeblocks/codeblocks.py
ghostcoder/codeblocks/coderepository.py
ghostcoder/codeblocks/parser/__init__.py
ghostcoder/codeblocks/parser/comment.py
ghostcoder/codeblocks/parser/create.py
ghostcoder/codeblocks/parser/java.py
ghostcoder/codeblocks/parser/javascript.py
ghostcoder/codeblocks/parser/parser.py
ghostcoder/codeblocks/parser/python.py
ghostcoder/codeblocks/parser/queries/__init__.py
ghostcoder/codeblocks/parser/queries/java.scm
ghostcoder/codeblocks/parser/queries/javascript.scm
ghostcoder/codeblocks/parser/queries/javascript_gpt.scm
ghostcoder/codeblocks/parser/queries/javascript_only.scm
ghostcoder/codeblocks/parser/queries/python.scm
ghostcoder/codeblocks/parser/queries/python_gpt.scm
ghostcoder/codeblocks/parser/queries/quuery_check.py
ghostcoder/codeblocks/parser/queries/typescript.scm
ghostcoder/codeblocks/parser/test.py
ghostcoder/codeblocks/parser/typescript.py
ghostcoder/create_exercise/__init__.py
ghostcoder/create_exercise/create_exercise.py
ghostcoder/create_exercise/prompts.py
ghostcoder/create_exercise/resources/no_deps/pom.xml
ghostcoder/display_callback.py
ghostcoder/filerepository.py
ghostcoder/index/__init__.py
ghostcoder/index/code_index.py
ghostcoder/index/code_knowledge_graph.py
ghostcoder/index/documentstore.py
ghostcoder/index/graphstore.py
ghostcoder/index/node_parser.py
ghostcoder/index/retriever.py
ghostcoder/index/schema.py
ghostcoder/index/testfil.py
ghostcoder/index/vectorstore.py
ghostcoder/ipython_callback.py
ghostcoder-0.0.13.dist-info/LICENSE
ghostcoder-0.0.13.dist-info/METADATA
ghostcoder-0.0.13.dist-info/WHEEL
ghostcoder-0.0.13.dist-info/RECORD
